silero_ocr/__init__.py
silero_ocr/model.py
silero_ocr/utils.py
silero_ocr/data/__init__.py
silero_ocr/data/word_symbols_vocab.txt
silero_ocr-0.9.0b0.dist-info/METADATA
silero_ocr-0.9.0b0.dist-info/WHEEL
silero_ocr-0.9.0b0.dist-info/licenses/LICENSE
silero_ocr-0.9.0b0.dist-info/RECORD
